umaudemc/__init__.py
umaudemc/__main__.py
umaudemc/api.py
umaudemc/backends.py
umaudemc/common.py
umaudemc/counterprint.py
umaudemc/distributed.py
umaudemc/formatter.py
umaudemc/formulae.py
umaudemc/grapher.py
umaudemc/gtk.py
umaudemc/jani.py
umaudemc/kleene.py
umaudemc/mproc.py
umaudemc/opsem.py
umaudemc/probabilistic.py
umaudemc/pyslang.py
umaudemc/quatex.py
umaudemc/resources.py
umaudemc/simulators.py
umaudemc/statistical.py
umaudemc/terminal.py
umaudemc/usermsgs.py
umaudemc/webui.py
umaudemc/wrappers.py
umaudemc/backend/__init__.py
umaudemc/backend/_pymc.py
umaudemc/backend/_spot.py
umaudemc/backend/_storm.py
umaudemc/backend/_stormpy.py
umaudemc/backend/bmcalc.py
umaudemc/backend/ltsmin.py
umaudemc/backend/nusmv.py
umaudemc/backend/prism.py
umaudemc/backend/pymc.py
umaudemc/backend/spin.py
umaudemc/backend/spot.py
umaudemc/backend/storm.py
umaudemc/command/__init__.py
umaudemc/command/check.py
umaudemc/command/graph.py
umaudemc/command/pcheck.py
umaudemc/command/scheck.py
umaudemc/command/sworker.py
umaudemc/command/test.py
umaudemc/data/__init__.py
umaudemc/data/opsem.maude
umaudemc/data/problog.maude
umaudemc/data/result.htm
umaudemc/data/select.htm
umaudemc/data/smcgraph.js
umaudemc/data/smcview.css
umaudemc/data/smcview.js
umaudemc/data/templog.maude
umaudemc-0.17.0.dist-info/licenses/LICENSE
umaudemc-0.17.0.dist-info/METADATA
umaudemc-0.17.0.dist-info/WHEEL
umaudemc-0.17.0.dist-info/entry_points.txt
umaudemc-0.17.0.dist-info/top_level.txt
umaudemc-0.17.0.dist-info/RECORD
